gson/__init__.py
gson/gmarshal.py
gson/decorators/safe_run.py
gson-0.0.4.dist-info/LICENSE
gson-0.0.4.dist-info/METADATA
gson-0.0.4.dist-info/WHEEL
gson-0.0.4.dist-info/top_level.txt
gson-0.0.4.dist-info/RECORD
