Metadata-Version: 2.1
Name: gson
Version: 0.0.4
Summary: Json Encode/Decoder in Golang Style
Author-email: Cruise Li <lhrotk@gmail.com>
Project-URL: Homepage, https://github.com/lhrotk/gson
Project-URL: Bug Tracker, https://github.com/lhrotk/gson/issues
Classifier: Programming Language :: Python :: 3
Classifier: License :: OSI Approved :: MIT License
Classifier: Operating System :: OS Independent
Requires-Python: >=3.8
License-File: LICENSE
